httpie_firebase_auth.py
httpie_firebase_auth-0.5.1.dist-info/entry_points.txt
httpie_firebase_auth-0.5.1.dist-info/LICENSE
httpie_firebase_auth-0.5.1.dist-info/WHEEL
httpie_firebase_auth-0.5.1.dist-info/METADATA
httpie_firebase_auth-0.5.1.dist-info/RECORD
