Metadata-Version: 2.1
Name: httpie-firebase-auth
Version: 0.5.1
Summary: An auth plugin for HTTPie that authenticates a user against Firebase
Home-page: https://github.com/safarmer/httpie-firebase-auth
License: MIT
Author: Shane Farmer
Author-email: shane@secondbest.info
Requires-Python: >=3.7,<4
Classifier: Development Status :: 2 - Pre-Alpha
Classifier: Environment :: Console
Classifier: Intended Audience :: Developers
Classifier: Intended Audience :: System Administrators
Classifier: License :: OSI Approved :: BSD License
Classifier: License :: OSI Approved :: MIT License
Classifier: Programming Language :: Python
Classifier: Programming Language :: Python :: 3
Classifier: Programming Language :: Python :: 3 :: Only
Classifier: Programming Language :: Python :: 3.10
Classifier: Programming Language :: Python :: 3.7
Classifier: Programming Language :: Python :: 3.8
Classifier: Programming Language :: Python :: 3.9
Classifier: Topic :: Internet :: WWW/HTTP
Classifier: Topic :: Software Development
Classifier: Topic :: System :: Networking
Classifier: Topic :: Terminals
Classifier: Topic :: Text Processing
Classifier: Topic :: Utilities
Requires-Dist: google-auth (>=2.9.1,<3.0.0)
Requires-Dist: httpie (>=3.2.1,<4.0.0)
Requires-Dist: requests (>=2.28.1,<3.0.0)
Project-URL: Repository, https://github.com/safarmer/httpie-firebase-auth
